gask
